streamlit_date_events/__init__.py
streamlit_date_events/date_events.py
streamlit_date_events/frontend/package-lock.json
streamlit_date_events/frontend/package.json
streamlit_date_events/frontend/tsconfig.json
streamlit_date_events/frontend/build/asset-manifest.json
streamlit_date_events/frontend/build/index.html
streamlit_date_events/frontend/build/static/js/main.105a5e48.js
streamlit_date_events/frontend/build/static/js/main.105a5e48.js.LICENSE.txt
streamlit_date_events/frontend/build/static/js/main.105a5e48.js.map
streamlit_date_events/frontend/public/index.html
streamlit_date_events/frontend/src/DateEventPicker.tsx
streamlit_date_events/frontend/src/index.tsx
streamlit_date_events-0.2.3.dist-info/licenses/LICENSE.md
streamlit_date_events-0.2.3.dist-info/METADATA
streamlit_date_events-0.2.3.dist-info/WHEEL
streamlit_date_events-0.2.3.dist-info/top_level.txt
streamlit_date_events-0.2.3.dist-info/RECORD
