Metadata-Version: 2.4
Name: streamlit-date-events
Version: 0.2.3
Summary: An advanced Streamlit date input component with event markers and multiple display modes
Home-page: https://github.com/valdemarlarsen/better-streamlit-date-input
Author: Valdemar
Author-email: Valdemar <valdemarlarsen0608@gmail.com>
License: MIT
Project-URL: Homepage, https://github.com/valdemarlarsen/better-streamlit-date-input
Project-URL: Documentation, https://github.com/valdemarlarsen/better-streamlit-date-input#readme
Project-URL: Repository, https://github.com/valdemarlarsen/better-streamlit-date-input
Project-URL: Bug Tracker, https://github.com/valdemarlarsen/better-streamlit-date-input/issues
Keywords: streamlit,date-picker,calendar,events,component
Classifier: Development Status :: 4 - Beta
Classifier: Intended Audience :: Developers
Classifier: License :: OSI Approved :: MIT License
Classifier: Programming Language :: Python :: 3
Classifier: Programming Language :: Python :: 3.7
Classifier: Programming Language :: Python :: 3.8
Classifier: Programming Language :: Python :: 3.9
Classifier: Programming Language :: Python :: 3.10
Classifier: Programming Language :: Python :: 3.11
Classifier: Topic :: Software Development :: Libraries :: Python Modules
Classifier: Topic :: Software Development :: User Interfaces
Requires-Python: >=3.7
License-File: LICENSE.md
Requires-Dist: streamlit>=1.0.0
Dynamic: author
Dynamic: home-page
Dynamic: license-file
Dynamic: requires-python
